sitemapy/__init__.py
sitemapy/sitemapy.py
sitemapy-0.2.3.dist-info/licenses/LICENSE
sitemapy-0.2.3.dist-info/METADATA
sitemapy-0.2.3.dist-info/WHEEL
sitemapy-0.2.3.dist-info/top_level.txt
sitemapy-0.2.3.dist-info/RECORD
