Metadata-Version: 2.4
Name: sitemapy
Version: 0.2.3
Summary: Python package that generates SEO-friendly XML sitemaps
Author-email: Graham Schmidt <graham.n.schmidt@gmail.com>
License-Expression: MIT
Project-URL: Homepage, https://github.com/Graham-Schmidt/sitemapy
Project-URL: Issues, https://github.com/Graham-Schmidt/sitemapy/issues
Classifier: Programming Language :: Python :: 3
Classifier: Operating System :: OS Independent
Requires-Python: >=3.10
License-File: LICENSE
Requires-Dist: defusedxml==0.7.0
Provides-Extra: dev
Requires-Dist: pytest>=7.0; extra == "dev"
Dynamic: license-file
